djdt_pev2/__init__.py
djdt_pev2/apps.py
djdt_pev2/forms.py
djdt_pev2/panels/__init__.py
djdt_pev2/templates/djdt_pev2/panels/pev_iframe.html
djdt_pev2/templates/djdt_pev2/panels/sql.html
djdt_pev2/templates/djdt_pev2/panels/sql_explain.html
djdt_pev2/types.py
djdt_pev2/utils.py
djdt_pev2/views.py
djdt_pev2-0.2.2.dist-info/LICENSE
djdt_pev2-0.2.2.dist-info/WHEEL
djdt_pev2-0.2.2.dist-info/METADATA
djdt_pev2-0.2.2.dist-info/RECORD
