Metadata-Version: 2.1
Name: djdt-pev2
Version: 0.2.2
Summary: Django Debug Toolbar Postgress Exlain Visualizer 2 panel
Author: william chu
Author-email: williamchu@uptickhq.com
Requires-Python: >=3.7,<4.0
Classifier: Programming Language :: Python :: 3
Classifier: Programming Language :: Python :: 3.10
Classifier: Programming Language :: Python :: 3.7
Classifier: Programming Language :: Python :: 3.8
Classifier: Programming Language :: Python :: 3.9
Requires-Dist: django-debug-toolbar (>=3.2.0,<4.0.0)
Requires-Dist: sqlparse
